quaker_db/__init__.py
quaker_db/__main__.py
quaker_db/client.py
quaker_db/file.py
quaker_db/globals.py
quaker_db/query.py
quaker_db/utils.py
quaker_db-2.0.0.dist-info/LICENSE
quaker_db-2.0.0.dist-info/METADATA
quaker_db-2.0.0.dist-info/WHEEL
quaker_db-2.0.0.dist-info/entry_points.txt
quaker_db-2.0.0.dist-info/RECORD
