Metadata-Version: 2.1
Name: quaker-db
Version: 2.0.0
Summary: Lightweight python API to USGS earthquake dataset
License: GNU GPLv3
Author: BlakeJC94
Author-email: blakejamescook@gmail.com
Requires-Python: >=3.9,<4.0
Classifier: License :: Other/Proprietary License
Classifier: Programming Language :: Python :: 3
Classifier: Programming Language :: Python :: 3.9
Classifier: Programming Language :: Python :: 3.10
Classifier: Programming Language :: Python :: 3.11
Classifier: Programming Language :: Python :: 3.12
Requires-Dist: requests (>=2.29.0,<3.0.0)
